calistar/__init__.py
calistar/_version.py
calistar/calistar.py
calistar-0.1.3.dist-info/licenses/LICENSE
calistar-0.1.3.dist-info/METADATA
calistar-0.1.3.dist-info/WHEEL
calistar-0.1.3.dist-info/top_level.txt
calistar-0.1.3.dist-info/RECORD
